Workbook

Sheet Assumptions
A1: ASSUMPTIONS
A3: Category | B3: Input Name | C3: Base Case Value | D3: Stress Case Value | E3: Unit | F3: Source | G3: Rationale
A4: A. ENTITY PARAMETERS
A5: Entity | B5: Annual Revenue | C5: 45000000 | D5: 45000000 | E5: AUD | F5: Analytical assumption. Scaled to represent a mid-tier independent agri-input distributor operating 5 regional hubs across the WA grain belt. | G5: Mid-tier WA agri-input SME, 5 regional hubs. Revenue held flat in stress — volume reduction assumed offset by higher per-unit pricing. Direction of risk: downward.
A6: Entity | B6: Gross Margin — Base | C6: 0.115 | E6: % | F6: Elders FY2025 Investor Presentation (retail products segment 12.5%); adjusted downward SME adjustment: no proprietary products, smaller volumes, no backward integration. Advisory services (15% rev, ~35% margin) partially offsets tight product margin.
A8: B. OPERATING EXPENDITURE
A9: Opex | B9: Executive / Finance Salaries (3 FTE) | C9: 360000 | D9: 360000 | E9: AUD | F9: Directional: operations manager salary ranges WA ~$105k; senior management premium applied | G9: CEO, CFO, Supply Chain Manager. $120,000 per FTE. Regional WA SME senior management.
A10: Opex | B10: Agronomy / Account Manager Salaries (6 FTE) | C10: 570000 | D10: 570000 | E10: AUD | F10: Indeed AU: avg agronomist salary WA $83,929; ERI SalaryExpert Perth: $107,488 | G10: Midpoint applied at $95,000 per FTE. Field agronomists and account managers.
A11: Opex | B11: Operations / Warehouse / Driver Salaries (15 FTE) | C11: 1125000 | D11: 1125000 | E11: AUD | F11: Indeed AU: warehouse supervisor WA $71,086 (Jan 2026); truck driver WA avg $75-80k (May 2026) | G11: Blended rate $75,000 per FTE across hub workers, drivers, warehouse coordinators.
A12: Opex | B12: Fleet Operating Costs | C12: 400000 | D12: 400000 | E12: AUD | F12: Operational estimate. Based on 6 bulk fuel tankers at approximately $65,000 per vehicle per year and 5 forklifts at approximately $5,000 per year, covering fuel, maintenance, registration and insurance.
A13: Opex | B13: Warehouse Operating Costs | C13: 500000 | D13: 500000 | E13: AUD | F13: Operational estimate. Five owned regional warehouse facilities at approximately $100,000 per hub per year, covering utilities, dangerous goods compliance, insurance and maintenance. Facilities owned — no lease cost. | G13: 5 regional hubs. Utilities, insurance, maintenance, safety compliance. ~$100k per hub per year.
A14: Opex | B14: Administration / IT / Audit / Legal | C14: 200000 | D14: 200000 | E14: AUD | F14: Operational estimate. Covers financial statement audit (mandatory under Corporations Act s.301 given revenue exceeds $25m threshold), accounting software, legal retainer and general administration for a 24-person business. | G14: Standard SME back-office costs. 24-person business without dedicated finance function.
A15: Opex | B15: Bad Debt Provision | C15: 50000 | D15: 50000 | E15: AUD | F15: Derived from bad debt provision rate of 0.90% applied to base case receivables. Rate sourced from Nutrien Ltd 2025 Annual Report (international receivables allowance) and Atradius B2B Payment Practices — Australia 2025 (agri-food sector). | G15: Fixed at $50,000 in both scenarios. Stress scenario models payment delay not default — relationship-dependent customer base assumed to eventually pay. Provision held constant to isolate working capital timing effect as the primary stress driver.
A17: C. INPUT COST PARAMETERS — UREA SHOCK
A18: Input Costs | B18: Urea Price — Base (2025 annual avg) | C18: 422.7 | E18: USD/mt | F18: World Bank Commodities Price Data (Pink Sheet) | G18: 2025 full-year annual average. Base case COGS reflects this price.
A19: Input Costs | B19: Urea Price — Spot Stress (April 2026) | D19: 856.9 | E19: USD/mt | F19: World Bank Commodities Price Data (Pink Sheet) | G19: April 2026 monthly price. Sharp acceleration from Q4 2025.
A20: Input Costs | B20: Urea as % of Total COGS | C20: 0.35 | D20: 0.35 | E20: % | F20: Nutrien Ltd 2025 Annual Report — crop nutrients represent 49% of global retail crop input sales by product category. ABARES farm survey data — fertiliser accounts for approximately 13% of total broadacre farm cash costs. Conservative midpoint applied given WAS Ltd product mix.
A21: Input Costs | B21: Cost Pass-Through Rate to Farmers | C21: 0.7 | D21: 0.7 | E21: % | F21: Analytical derivation. WAS Ltd has no proprietary products and faces direct competition from Elders Limited and Nutrien Ag Solutions across all five hub locations. Full pass-through risks customer attrition to competing networks. Partial pass-through is standard for commodity input distributors during price spike periods.
A22: Input Costs | B22: Cost Absorbed by WAS Ltd | C22: 0.3 | D22: 0.3 | E22: % | F22: Calculated as complement of pass-through rate (1 − 70%). The 30% absorption rate preserves analytical tension between margin compression and working capital stress as concurrent drivers of the liquidity crisis.
A24: D. WORKING CAPITAL DRIVERS
A25: Working Capital | B25: Days Inventory Outstanding (DIO) | C25: 67 | D25: 67 | E25: Days | F25: (1) Freight Lines Group — Perth to Esperance and Geraldton daily freight service, confirming active fertiliser freight corridors (freightlinesgroup.com.au). (2) Kragt, M. — 'Winter crops need to be sown but Australia's farmers are worried about fertilisers and fuel', The Conversation, 2 April 2026 (UWA). (3) DPIRD — Western Australian Crop Sowing Guide 2026. | G25: WA regional geography: 300–500km freight from Perth port to Esperance and Geraldton creates minimum 2–3 week replenishment lead time. Distributor cannot run lean inventory under these logistics constraints. Pre-seeding fertiliser buildup April–June requires warehouse stock 4–6 weeks prior. DIO held constant across base and stress — supply chain lead time constraint applies equally in both scenarios. DSO deterioration is the primary working capital stress driver.
A26: Working Capital | B26: Days Sales Outstanding (DSO) — Base | C26: 45 | E26: Days | F26: Atradius — B2B Payment Practices Barometer, Australia 2024: average payment terms 35 days, extended by nearly two weeks from prior period. ScaleSuite — Australian SME Finance Operations Benchmark Report 2026: industry-wide debtor days 45–65 days. | G26: 30-day standard trade terms + 15-day collection lag. 24-person business has no dedicated credit controller. Direction of risk: upward.
A27: Working Capital | B27: Days Sales Outstanding (DSO) — Stress | D27: 80 | E27: Days | F27: Atradius — B2B Payment Practices Trends, Australia 2025: Australian agri-food companies specifically flagged for DSO deterioration and growing liquidity challenges from extended payment terms. ABARES farm survey data: fertiliser represents 13% of total broadacre farm cash costs — input price spike directly compresses farmer liquidity. | G27: Farmer cash flow squeeze forces payment extension from 30-day toward 60-90 day terms. Relationship dependency prevents aggressive enforcement. 80 days conservative relative to theoretical maximum (harvest income not until Nov-Dec). Note: price acceptance and payment timing represent distinct farmer decisions — producers facing a mandatory pre-seeding input purchase will accept higher prices to secure supply while managing cash flow pressure by extending payment beyond standard terms.
A28: Working Capital | B28: Days Payable Outstanding (DPO) — Base | C28: 32 | E28: Days | F28: Analytical derivation. Named upstream suppliers (Incitec Pivot Fertilisers, Nufarm Australia, Syngenta, Ampol Australia, BP Wholesale) are large multinationals or ASX-listed corporates. Standard SME trade credit terms enforced at 30 days with no negotiating leverage available to a $45m independent distributor. | G28: Suppliers (Incitec Pivot, Nufarm, Syngenta, Ampol, BP) are large multinationals. SME at $45m revenue has no leverage to extend terms. Supply disruption during seeding = existential risk. Enforces prompt payment. 30-day terms + 2-day processing margin.
A29: Working Capital | B29: Days Payable Outstanding (DPO) — Stress | D29: 30 | E29: Days | F29: Analytical derivation. Supplier tightening assumed under credit stress conditions. | G29: Suppliers may tighten under credit stress. 2-day reduction immaterial (~$219k cash impact) — included for completeness — not presented as a key stress driver in findings.
A31: E. COST OF CAPITAL & RATES
A32: Market Rates | B32: Overdraft Rate | C32: 0.1051 | D32: 0.1051 | E32: % p.a. | F32: Reserve Bank of Australia — Indicator Lending Rates, Table F5: small business variable overdraft rate, April 2026: 10.51% per annum. | G32: Applied to incremental working capital gap in stress. Base case overdraft draw is zero — see Section C
A33: Market Rates | B33: Overdraft Interest — Base | C33: 0 | E33: AUD | F33: Stated assumption | G33: Base case assumes no overdraft draw under normal operating conditions
A34: Market Rates | B34: Superannuation Guarantee Rate | C34: 0.12 | D34: 0.12 | E34: % | F34: ATO — Key Superannuation Rates and Thresholds FY2025-26. Rate from 1 July 2025. Final legislated increase. | G34: Applied to total salary bill across all 24 FTE. Legislated minimum — no discretion available to employer.
A35: Market Rates | B35: Bad Debt Provision Rate | C35: 0.009 | D35: 0.009 | E35: % | F35: Nutrien Ltd 2025 Annual Report — international (Australian) receivables allowance: approximately 0.90% of gross receivables. Atradius — B2B Payment Practices Trends, Australia 2025: agri-food sector bad debt experience consistent with this range. | G35: Reference rate only. Used to derive bad debt provision in CCC_Model tab. Held constant in stress — stress scenario models payment delay not default risk.
A36: Market Rates | B36: Perth Wholesale Diesel Price | C36: 197.1 | D36: 197.1 | E36: cents/litre | F36: Australian Institute of Petroleum — Terminal Gate Price, Perth, 28 May 2026: 197.1 cents per litre (inclusive of GST). Data prepared by ORIMA Research on behalf of AIP using submissions from BP Australia, Ampol, Viva Energy Australia and ExxonMobil. | G36: Reference rate for diesel inventory carrying cost. Perth lowest of all capitals — consistent with proximity to Kwinana terminal.
A37: Market Rates | B37: DAP Fertiliser Price — April 2026 | C37: 725.3 | D37: 725.3 | E37: USD/mt | F37: World Bank Commodities Price Data (Pink Sheet), May 2026 edition. DAP (diammonium phosphate), spot price, f.o.b. US Gulf, April 2026. | G37: Secondary fertiliser reference. Confirms broader fertiliser price pressure beyond urea.
A38: Market Rates | B38: ABS Transport Sector Median Weekly Earnings | C38: 1470 | D38: 1470 | E38: AUD/week | F38: Australian Bureau of Statistics — Average Weekly Earnings, transport, postal and warehousing sector, August 2025: median weekly earnings $1,470. | G38: Directional support for operations/driver salary assumptions. Annualised: ~$76,440. Consistent with $75,000 applied.
A40: F. DISCLAIMER
A41: Wheatbelt Agronomy Supplies Ltd is a fictional entity created for illustrative purposes. All financial inputs are derived from publicly available data sources as cited. Working capital metrics are derived from first-principles operational reasoning and publicly available industry benchmarks; a real engagement would replace these estimates with actual ledger data extracted from the company's accounting system. This analysis does not constitute financial or investment advice.

Sheet CCC_Model
A1: CCC MODEL — WHEATBELT AGRONOMY SUPPLIES LTD
A3: # | B3: Line Item | C3: Base Case | D3: Stress Case | E3: Variance ($) | F3: Variance (%)
A4: 1. INCOME STATEMENT SUMMARY
A5: 1.1 | B5: Revenue | C5: =Assumptions!C5 -> 45000000 | D5: =Assumptions!D5 -> 45000000 | E5: =D5-C5 -> 0 | F5: =E5/C5 -> 0
A6: 1.2 | B6: Cost of Goods Sold (COGS) | C6: =C5*(1-Assumptions!C6) -> 39825000 | D6: =C6 + (C6 * Assumptions!C20 * Assumptions!C22 * ((Assumptions!D19 + Assumptions!C18)/2 - Assumptions!C18) / Assumptions!C18) -> 41972695 | E6: =D6-C6 -> 2147695.3 | F6: =E6/C6 -> 0.053928318
A7: 1.3 | B7: Gross Profit | C7: =C5-C6 -> 5175000 | D7: =D5-D6 -> 3027304.7 | E7: =D7-C7 -> -2147695.3 | F7: =E7/C7 -> -0.41501358
A8: 1.4 | B8: Gross Margin % | C8: =C7/C5 -> 0.115 | D8: =D7/D5 -> 0.067273439 | E8: =D8-C8 -> -0.047726561
A9: 1.5 | B9: Total Operating Expenditure | C9: =SUM(Assumptions!C9:C15)+Assumptions!C34*SUM(Assumptions!C9:C11) -> 3451600 | D9: =C9 -> 3451600 | E9: =D9-C9 -> 0 | F9: =E9/C9 -> 0
A10: 1.6 | B10: Operating Profit Before Overdraft Interest | C10: =C7-C9 -> 1723400 | D10: =D7-D9 -> -424295.26 | E10: =D10-C10 -> -2147695.3 | F10: =E10/ABS(C10) -> -1.2461966
A11: 1.7 | B11: Overdraft Interest Cost | C11: =Assumptions!C33 -> 0 | D11: =D32 -> 499330.02 | E11: =D11-C11 -> 499330.02 | F11: =E11/ABS(C10) -> 0.28973542
A12: 1.8 | B12: Net Profit | C12: =C10-C11 -> 1723400 | D12: =D10-D11 -> -923625.28 | E12: =D12-C12 -> -2647025.3 | F12: =E12/ABS(C12) -> -1.535932
A13: 1.9 | B13: Net Margin % | C13: =C12/C5 -> 0.038297778 | D13: =D12/D5 -> -0.020525006 | E13: =D13-C13 -> -0.058822784
A15: 2. WORKING CAPITAL DRIVERS
A16: 2.1 | B16: Days Inventory Outstanding (DIO) | C16: =Assumptions!C25 -> 67 | D16: =Assumptions!D25 -> 67 | E16: =D16-C16 -> 0
A17: 2.2 | B17: Days Sales Outstanding (DSO) | C17: =Assumptions!C26 -> 45 | D17: =Assumptions!D27 -> 80 | E17: =D17-C17 -> 35
A18: 2.3 | B18: Days Payable Outstanding (DPO) | C18: =Assumptions!C28 -> 32 | D18: =Assumptions!D29 -> 30 | E18: =D18-C18 -> -2
A19: 2.4 | B19: Cash Conversion Cycle (CCC) | C19: =C16+C17-C18 -> 80 | D19: =D16+D17-D18 -> 117 | E19: =D19-C19 -> 37 | F19: =E19/C19 -> 0.4625
A20: 2.5 | B20: CCC Deterioration (Stress vs Base) | E20: =D19-C19 -> 37
A22: 3. WORKING CAPITAL BALANCES
A23: 3.1 | B23: Inventory | C23: =C6*C16/365 -> 7310342.5 | D23: =D6*D16/365 -> 7704576.9 | E23: =D23-C23 -> 394234.47 | F23: =E23/C23 -> 0.053928318
A24: 3.2 | B24: Trade Receivables | C24: =C5*C17/365 -> 5547945.2 | D24: =D5*D17/365 -> 9863013.7 | E24: =D24-C24 -> 4315068.5 | F24: =E24/C24 -> 0.77777778
A25: 3.3 | B25: Trade Payables | C25: =C6*C18/365 -> 3491506.8 | D25: =D6*D18/365 -> 3449810.6 | E25: =D25-C25 -> -41696.28 | F25: =E25/C25 -> -0.011942202
A26: 3.4 | B26: Net Working Capital (NWC) | C26: =C23+C24-C25 -> 9366780.8 | D26: =D23+D24-D25 -> 14117780 | E26: =D26-C26 -> 4750999.2 | F26: =E26/C26 -> 0.50721794
A27: 3.5 | B27: Incremental WC Gap (Stress vs Base) | D27: =D26-C26 -> 4750999.2
A29: 4. OVERDRAFT COST ANALYSIS
A30: 4.1 | B30: Incremental WC Gap (Stress vs Base) | D30: =D27 -> 4750999.2
A31: 4.2 | B31: Overdraft Rate (RBA F5, April 2026) | C31: =Assumptions!C32 -> 0.1051 | D31: =Assumptions!D32 -> 0.1051
A32: 4.3 | B32: Overdraft Interest Cost — Stress | C32: =Assumptions!C33 -> 0 | D32: =D30*D31 -> 499330.02 | E32: =D32-C32 -> 499330.02
A33: 4.4 | B33: Overdraft Interest as % of Base Net Profit | D33: =D32/C12 -> 0.28973542
A34: 4.5 | B34: Overdraft Cost as % of Total Earnings Swing | D34: =D32/ABS(D12-C12) -> 0.18863818
A36: 5. EARNINGS BRIDGE — BASE TO STRESS
A37: 5.1 | B37: Base Net Profit | C37: =C12 -> 1723400
A38: 5.2 | B38: Less: Gross Margin Compression (Urea Absorption) | D38: =D7-C7 -> -2147695.3 | F38: =D38/ABS(C37) -> -1.2461966
A39: 5.3 | B39: Less: Overdraft Interest Cost (Stress) | D39: =-D32 -> -499330.02 | F39: =D39/ABS(C37) -> -0.28973542
A40: 5.4 | B40: Equals: Stress Net Profit | C40: =C37+D38+D39 -> -923625.28
A41: 5.5 | B41: Total Earnings Swing (Base to Stress) | D41: =D40-C37 -> -1723400
A42: 5.6 | B42: Margin Compression as % of Total Swing | D42: =D38/D41 -> 1.2461966
A43: 5.7 | B43: Overdraft Cost as % of Total Swing | D43: =D39/D41 -> 0.28973542
A45: KEY FINDINGS
A46: Gross margin compression from urea cost absorption is the dominant stress driver, contributing 81% of the total earnings deterioration. Working capital deterioration from debtor payment extension compounds the position but is secondary — contributing 19% of the swing. The business cannot trade its way out of this crisis through working capital management alone. Pricing recovery is the critical lever.

Sheet Scenarios
A1: SCENARIO ANALYSIS — WHEATBELT AGRONOMY SUPPLIES LTD
A3: RECOVERY CASE ASSUMPTIONS (HARDCODED INPUTS)
A4: DSO Recovery | C4: 60 | D4: Days — partial improvement via early payment discount offer
A5: Early Payment Discount Rate | C5: 0.015 | D5: % offered to farmers paying within 14 days
A6: Discount Uptake Rate | C6: 0.3 | D6: % of receivables accepting the offer
A7: DIO Recovery | C7: 57 | D7: Days — inventory drawdown, reduce pre-seeding stock build
A8: DPO Recovery | C8: 35 | D8: Days — partial extension negotiated with one supplier
A10: # | B10: Line Item | C10: Base Case | D10: Stress Case | E10: Recovery Case | F10: Variance: Base vs Stress | G10: Variance: Base vs Recovery
A11: SECTION 1 - INCOME STATEMENT
A12: 1.1 | B12: Revenue | C12: =Assumptions!C5 -> 45000000 | D12: =Assumptions!D5 -> 45000000 | E12: =Assumptions!C5 -> 45000000 | F12: =D12-C12 -> 0 | G12: =E12-C12 -> 0
A13: 1.2 | B13: COGS | C13: =CCC_Model!C6 -> 39825000 | D13: =CCC_Model!D6 -> 41972695 | E13: =D13 -> 41972695 | F13: =D13-C13 -> 2147695.3 | G13: =E13-C13 -> 2147695.3
A14: 1.3 | B14: Gross Profit | C14: =C12-C13 -> 5175000 | D14: =D12-D13 -> 3027304.7 | E14: =E12-E13 -> 3027304.7 | F14: =D14-C14 -> -2147695.3 | G14: =E14-C14 -> -2147695.3
A15: 1.4 | B15: Gross Margin % | C15: =C14/C12 -> 0.115 | D15: =D14/D12 -> 0.067273439 | E15: =D14/D12 -> 0.067273439 | F15: =D15-C15 -> -0.047726561 | G15: =E15-C15 -> -0.047726561
A16: 1.5 | B16: Total Operating Expenditure | C16: =CCC_Model!C9 -> 3451600 | D16: =CCC_Model!D9 -> 3451600 | E16: =C16 -> 3451600
A17: 1.6 | B17: Operating Profit Before Overdraft | C17: =C14-C16 -> 1723400 | D17: =D14-D16 -> -424295.26 | E17: =E14-E16 -> -424295.26
A18: 1.7 | B18: Early Payment Discount Cost | C18: =0 -> 0 | D18: 0 | E18: =(E12*C4/365) * C5 * C6 -> 33287.671
A19: 1.8 | B19: Overdraft Interest Cost | C19: =Assumptions!C33 -> 0 | D19: =CCC_Model!D32 -> 499330.02 | E19: =(((Assumptions!C5 * C4/365)+(C13*C7/365)-(C13*C8/365)) - CCC_Model!C26)*Assumptions!C32 -> 45286.582
A20: 1.9 | B20: Net Profit | C20: =C17-C18-C19 -> 1723400 | D20: =D17-D18-D19 -> -923625.28 | E20: =E17-E18-E19 -> -502869.52 | F20: =D20-C20 -> -2647025.3 | G20: =E20-C20 -> -2226269.5
A21: 1.1 | B21: Net Margin % | C21: =C20/C12 -> 0.038297778 | D21: =D20/D12 -> -0.020525006 | E21: =E20/E12 -> -0.011174878 | F21: =D21-C21 -> -0.058822784 | G21: =E21-C21 -> -0.049472656
A23: SECTION 2 - WORKING CAPITAL METRICS
A24: 2.1 | B24: Days Inventory Outstanding (DIO) | C24: =Assumptions!C25 -> 67 | D24: =Assumptions!D25 -> 67 | E24: =C7 -> 57 | F24: =D24-C24 -> 0 | G24: =E24-C24 -> -10
A25: =A24+0.1 -> 2.2 | B25: Days Sales Outstanding (DSO) | C25: =Assumptions!C26 -> 45 | D25: =Assumptions!D27 -> 80 | E25: =C4 -> 60 | F25: =D25-C25 -> 35 | G25: =E25-C25 -> 15
A26: =A25+0.1 -> 2.3 | B26: Days Payable Outstanding (DPO) | C26: =Assumptions!C28 -> 32 | D26: =Assumptions!D29 -> 30 | E26: =C8 -> 35 | F26: =D26-C26 -> -2 | G26: =E26-C26 -> 3
A27: =A26+0.1 -> 2.4 | B27: Cash Conversion Cycle (CCC) | C27: =C24+C25-C26 -> 80 | D27: =D24+D25-D26 -> 117 | E27: =E24+E25-E26 -> 82 | F27: =D27-C27 -> 37 | G27: =E27-C27 -> 2
A28: =A27+0.1 -> 2.5 | B28: Inventory | C28: =CCC_Model!C23 -> 7310342.5 | D28: =CCC_Model!D23 -> 7704576.9 | E28: =E13*E24/365 -> 6554640.1
A29: =A28+0.1 -> 2.6 | B29: Receivables | C29: =CCC_Model!C24 -> 5547945.2 | D29: =CCC_Model!D24 -> 9863013.7 | E29: =E12*E25/365 -> 7397260.3
A30: =A29+0.1 -> 2.7 | B30: Payables | C30: =CCC_Model!C25 -> 3491506.8 | D30: =CCC_Model!D25 -> 3449810.6 | E30: =E13*E26/365 -> 4024779
A31: =A30+0.1 -> 2.8 | B31: Net Working Capital (NWC) | C31: =CCC_Model!C26 -> 9366780.8 | D31: =CCC_Model!D26 -> 14117780 | E31: =E28+E29-E30 -> 9927121.4
A32: =A31+0.1 -> 2.9 | B32: Incremental WC Gap vs Base | D32: =D31-C31 -> 4750999.2 | E32: =E31-C31 -> 560340.54 | G32: =E32-D32 -> -4190658.7
A34: SECTION 3 - SCENARIO SUMMARY
A35: 3.1 | B35: Net Profit | C35: =C20 -> 1723400 | D35: =D20 -> -923625.28 | E35: =E20 -> -502869.52
A36: =A35+0.1 -> 3.2 | B36: Net Margin % | C36: =C21 -> 0.038297778 | D36: =D21 -> -0.020525006 | E36: =E21 -> -0.011174878
A37: =A36+0.1 -> 3.3 | B37: CCC | C37: =C27 -> 80 | D37: =D27 -> 117 | E37: =E27 -> 82
A38: =A37+0.1 -> 3.4 | B38: NWC | C38: =C31 -> 9366780.8 | D38: =D31 -> 14117780 | E38: =E31 -> 9927121.4
A39: =A38+0.1 -> 3.5 | B39: Overdraft Interest Cost | C39: =C19 -> 0 | D39: =D19 -> 499330.02 | E39: =E19 -> 45286.582
A40: =A39+0.1 -> 3.6 | B40: Earnings vs Base Case | D40: =D35-C35 -> -2647025.3 | E40: =E35-C35 -> -2226269.5 | G40: =E40-D40 -> 420755.77
A41: =A40+0.1 -> 3.7 | B41: Recovery Improvement vs Stress | E41: =E35-D35 -> 420755.77
A42: =A41+0.1 -> 3.8 | B42: Recovery Improvement as % of Stress Loss | E42: =E41/ABS(D35) -> 0.45554813
A44: KEY FINDINGS
A45: Recovery levers reduce but do not eliminate the stress loss. The three operational actions — early payment discount, inventory drawdown, and supplier term extension — nearly restore working capital efficiency (CCC: 82 days vs base 80 days) but gross margin compression from urea cost absorption remains the dominant unresolved threat. Pricing recovery is required to return the business to profitability.

Sheet Sensitivity
A1: SENSITIVITY ANALYSIS — NET PROFIT UNDER VARYING CONDITIONS
A4: DSO Input (days) | B4: 80 | C4: Adjust these inputs to test individual scenarios — table updates automatically | L4: =Assumptions!C5*(1-Assumptions!C6)*(1+Assumptions!C20*(1-B5)*((Assumptions!D19+Assumptions!C18)/2-Assumptions!C18)/Assumptions!C18) -> 41972695
A5: Pass-Through Rate Input | B5: 0.7 | L5: =Assumptions!C5-L4 -> 3027304.7
L6: =Assumptions!C5*B4/365 -> 9863013.7
A7: NET PROFIT ($) — DSO vs UREA PASS-THROUGH RATE | L7: =L6+(L4*Assumptions!C25/365)-(L4*Assumptions!C28/365) -> 13887793
C8: Urea Cost Pass-Through Rate to Farmers | L8: =MAX(0,L7-((Assumptions!C5*Assumptions!C26/365)+(L4*Assumptions!C25/365)-(L4*Assumptions!C28/365))) -> 4315068.5
B9: =L10 -> -877808.96 | C9: 0.4 | D9: =C9+10% -> 0.5 | E9: =D9+10% -> 0.6 | F9: =E9+10% -> 0.7 | G9: =F9+10% -> 0.8 | H9: =G9+10% -> 0.9 | I9: =H9+10% -> 1 | L9: =L8*Assumptions!C32 -> 453513.7
A10: Days Sales Outstanding (DSO) | B10: 45 | C10: -2571990.5 | D10: -1856092.1 | E10: -1140193.7 | F10: -424295.26 | G10: 291603.16 | H10: 1007501.6 | I10: 1723400 | K10: Master Formula (Net Profit) | L10: =L5-(Assumptions!C9+Assumptions!C10+Assumptions!C11+Assumptions!C12+Assumptions!C13+Assumptions!C14+Assumptions!C15+Assumptions!C34*(Assumptions!C9+Assumptions!C10+Assumptions!C11))-L9 -> -877808.96
B11: =B10+5 -> 50 | C11: -2636778.2 | D11: -1920879.8 | E11: -1204981.4 | F11: -489082.93 | G11: 226815.49 | H11: 942713.91 | I11: 1658612.3
B12: =B11+5 -> 55 | C12: -2701565.9 | D12: -1985667.4 | E12: -1269769 | F12: -553870.61 | G12: 162027.82 | H12: 877926.24 | I12: 1593824.7
B13: =B12+5 -> 60 | C13: -2766353.5 | D13: -2050455.1 | E13: -1334556.7 | F13: -618658.28 | G13: 97240.145 | H13: 813138.57 | I13: 1529037
B14: =B13+5 -> 65 | C14: -2831141.2 | D14: -2115242.8 | E14: -1399344.4 | F14: -683445.95 | G14: 32452.473 | H14: 748350.89 | I14: 1464249.3
B15: =B14+5 -> 70 | C15: -2895928.9 | D15: -2180030.5 | E15: -1464132 | F15: -748233.62 | G15: -32335.198 | H15: 683563.22 | I15: 1399461.6
B16: =B15+5 -> 75 | C16: -2960716.6 | D16: -2244818.1 | E16: -1528919.7 | F16: -813021.29 | G16: -97122.869 | H16: 618775.55 | I16: 1334674
B17: =B16+5 -> 80 | C17: -3025504.2 | D17: -2309605.8 | E17: -1593707.4 | F17: -877808.96 | G17: -161910.54 | H17: 553987.88 | I17: 1269886.3
B18: =B17+5 -> 85 | C18: -3090291.9 | D18: -2374393.5 | E18: -1658495.1 | F18: -942596.63 | G18: -226698.21 | H18: 489200.21 | I18: 1205098.6
B19: =B18+5 -> 90 | C19: -3155079.6 | D19: -2439181.1 | E19: -1723282.7 | F19: -1007384.3 | G19: -291485.88 | H19: 424412.54 | I19: 1140311
B20: =B19+5 -> 95 | C20: -3219867.2 | D20: -2503968.8 | E20: -1788070.4 | F20: -1072172 | G20: -356273.55 | H20: 359624.87 | I20: 1075523.3
B21: =B20+5 -> 100 | C21: -3284654.9 | D21: -2568756.5 | E21: -1852858.1 | F21: -1136959.6 | G21: -421061.23 | H21: 294837.2 | I21: 1010735.6
